fast_bunkai-0.1.1.dist-info/METADATA
fast_bunkai-0.1.1.dist-info/WHEEL
fast_bunkai-0.1.1.dist-info/entry_points.txt
fast_bunkai/__init__.py
fast_bunkai/_fast_bunkai.pyd
fast_bunkai/_fast_bunkai.pyi
fast_bunkai/annotations.py
fast_bunkai/cli.py
fast_bunkai/core.py
fast_bunkai-0.1.1.dist-info/RECORD
