Metadata-Version: 2.4
Name: fast-bunkai
Version: 0.1.1
Requires-Dist: janome>=0.5.0
Summary: Rust-accelerated sentence boundary detection compatible with bunkai
Requires-Python: >=3.10
